cliapi.py
cliapi-1.1.dist-info/LICENSE
cliapi-1.1.dist-info/WHEEL
cliapi-1.1.dist-info/METADATA
cliapi-1.1.dist-info/RECORD
