Metadata-Version: 2.1
Name: cliapi
Version: 1.1
Summary: Cliapi 是一个专为 Python 初学者设计的 WEB 包，目的是让学者能够以非常简单的方式搭建一个 WEB 服务，进而提高对 Python 的兴趣，步入 Python 世界。
Keywords: tornado,flask,fastapi,django,cliapi
Author-email: 江南雨上 <lcctoor@outlook.com>
Classifier: License :: OSI Approved :: Apache Software License
Requires-Dist: arts>=2024.7.30
Project-URL: Source, https://github.com/lcctoor/arts/tree/main/arts/cliapi
